hxwxpy/__init__.py
hxwxpy/api_sendtext.py
hxwxpy/word_filter.py
hxwxpy-0.0.4.5.data/data/lib/hx_txt/wd.txt
hxwxpy-0.0.4.5.dist-info/METADATA
hxwxpy-0.0.4.5.dist-info/WHEEL
hxwxpy-0.0.4.5.dist-info/top_level.txt
hxwxpy-0.0.4.5.dist-info/RECORD
