Metadata-Version: 2.1
Name: hxwxpy
Version: 0.0.4.5
Summary: Interface of docking section, enabling robots to send WeChat messages
Home-page: UNKNOWN
Author: mldsh
Author-email: LiuHao88888@88.com
License: MIT
Platform: UNKNOWN
Requires-Dist: requests
